git_changes.py
git_changes-0.0.3.dist-info/licenses/LICENSE
git_changes-0.0.3.dist-info/METADATA
git_changes-0.0.3.dist-info/WHEEL
git_changes-0.0.3.dist-info/entry_points.txt
git_changes-0.0.3.dist-info/top_level.txt
git_changes-0.0.3.dist-info/RECORD
