Metadata-Version: 2.4
Name: git-changes
Version: 0.0.3
Summary: A way to manage commit messages
Author-email: Adwaith-Rajesh <me@adwaith.dev>
License-Expression: MIT
Project-URL: Homepage, https://github.com/Adwaith-Rajesh/git-changes
Classifier: Programming Language :: Python :: 3
Classifier: Operating System :: OS Independent
Requires-Python: >=3.12
License-File: LICENSE
Dynamic: license-file
